NewtonLaws/LawOfForce.py
NewtonLaws/LawsOfMotion.py
NewtonLaws/Maths.py
NewtonLaw-0.2.dist-info/METADATA
NewtonLaw-0.2.dist-info/WHEEL
NewtonLaw-0.2.dist-info/top_level.txt
NewtonLaw-0.2.dist-info/RECORD
