Metadata-Version: 2.1
Name: NewtonLaw
Version: 0.2
Summary: this is program to enable programmers not to write big code for calculating the laws of Newton and Maths formulae
Home-page: UNKNOWN
Author: Ashmit Jain
Author-email: ashmitjain023@gmail.com
License: UNKNOWN
Platform: UNKNOWN
